source_facebook_marketing/README.md
source_facebook_marketing/__init__.py
source_facebook_marketing/api.py
source_facebook_marketing/config_migrations.py
source_facebook_marketing/run.py
source_facebook_marketing/schemas/activities.json
source_facebook_marketing/schemas/ad_account.json
source_facebook_marketing/schemas/ad_creatives.json
source_facebook_marketing/schemas/ad_sets.json
source_facebook_marketing/schemas/ads.json
source_facebook_marketing/schemas/ads_insights.json
source_facebook_marketing/schemas/ads_insights_action_breakdowns.json
source_facebook_marketing/schemas/ads_insights_breakdowns.json
source_facebook_marketing/schemas/ads_insights_custom_fields.json
source_facebook_marketing/schemas/campaigns.json
source_facebook_marketing/schemas/custom_audiences.json
source_facebook_marketing/schemas/custom_conversions.json
source_facebook_marketing/schemas/images.json
source_facebook_marketing/schemas/shared/ads_action_stats.json
source_facebook_marketing/schemas/shared/ads_histogram_stats.json
source_facebook_marketing/schemas/shared/ads_image_crops.json
source_facebook_marketing/schemas/shared/ads_insights_dda_result.json
source_facebook_marketing/schemas/shared/ads_insights_result.json
source_facebook_marketing/schemas/shared/geo_locations.json
source_facebook_marketing/schemas/shared/targeting.json
source_facebook_marketing/schemas/videos.json
source_facebook_marketing/source.py
source_facebook_marketing/spec.py
source_facebook_marketing/streams/__init__.py
source_facebook_marketing/streams/async_job.py
source_facebook_marketing/streams/async_job_manager.py
source_facebook_marketing/streams/base_insight_streams.py
source_facebook_marketing/streams/base_streams.py
source_facebook_marketing/streams/common.py
source_facebook_marketing/streams/patches.py
source_facebook_marketing/streams/streams.py
source_facebook_marketing/utils.py
airbyte_source_facebook_marketing-4.2.0.dist-info/METADATA
airbyte_source_facebook_marketing-4.2.0.dist-info/WHEEL
airbyte_source_facebook_marketing-4.2.0.dist-info/entry_points.txt
airbyte_source_facebook_marketing-4.2.0.dist-info/RECORD
