Metadata-Version: 2.1
Name: airbyte-source-facebook-marketing
Version: 4.2.0
Summary: Source implementation for Facebook Marketing.
Home-page: https://airbyte.com
License: ELv2
Author: Airbyte
Author-email: contact@airbyte.io
Requires-Python: >=3.10,<3.12
Classifier: License :: Other/Proprietary License
Classifier: Programming Language :: Python :: 3
Classifier: Programming Language :: Python :: 3.10
Classifier: Programming Language :: Python :: 3.11
Requires-Dist: airbyte-cdk (>=7.4.1,<8.0.0)
Requires-Dist: cached-property (>=2,<3)
Requires-Dist: facebook-business (>=23.0.0,<24.0.0)
Project-URL: Documentation, https://docs.airbyte.com/integrations/sources/facebook-marketing
Project-URL: Repository, https://github.com/airbytehq/airbyte
